kotka/__init__.py
kotka/lipogram/__init__.py
kotka/lipogram/rules.py
kotka/shredder/__init__.py
kotka/utils/__init__.py
kotka/utils/dictionary.py
kotka/utils/hangul.py
kotka/yaminizer/__init__.py
kotka-0.1.1.dist-info/LICENSE
kotka-0.1.1.dist-info/METADATA
kotka-0.1.1.dist-info/WHEEL
kotka-0.1.1.dist-info/top_level.txt
kotka-0.1.1.dist-info/RECORD
