Metadata-Version: 2.1
Name: kotka
Version: 0.1.1
Summary: Korean Obfuscation ToolKit Advanced
Home-page: https://github.com/Astro36/kotka
Author: Seungjae Park
Author-email: astro.psj@gmail.com
License: MIT
Keywords: korean-nlp,korean-text-processing,hangul,toolkit
Platform: UNKNOWN
Classifier: Development Status :: 4 - Beta
Classifier: Intended Audience :: Developers
Classifier: Intended Audience :: Science/Research
Classifier: License :: OSI Approved :: MIT License
Classifier: Natural Language :: Korean
Classifier: Operating System :: OS Independent
Classifier: Programming Language :: Python :: 3.6
Classifier: Programming Language :: Python :: 3.7
Classifier: Programming Language :: Python :: 3.8
Classifier: Topic :: Scientific/Engineering :: Artificial Intelligence
Classifier: Topic :: Scientific/Engineering :: Information Analysis
Classifier: Topic :: Software Development :: Libraries :: Python Modules
Classifier: Topic :: Text Processing :: Linguistic
Requires-Python: >=3.6
